cryptolyzer/__init__.py
cryptolyzer/__main__.py
cryptolyzer/__setup__.py
cryptolyzer/common/__init__.py
cryptolyzer/common/analyzer.py
cryptolyzer/common/application.py
cryptolyzer/common/dhparam.py
cryptolyzer/common/exception.py
cryptolyzer/common/prime.py
cryptolyzer/common/result.py
cryptolyzer/common/transfer.py
cryptolyzer/common/utils.py
cryptolyzer/common/vulnerability.py
cryptolyzer/common/x509.py
cryptolyzer/dnsrec/__init__.py
cryptolyzer/dnsrec/analyzer.py
cryptolyzer/dnsrec/client.py
cryptolyzer/dnsrec/dnssec.py
cryptolyzer/dnsrec/mail.py
cryptolyzer/dnsrec/transfer.py
cryptolyzer/hassh/__init__.py
cryptolyzer/hassh/analyzer.py
cryptolyzer/hassh/generate.py
cryptolyzer/httpx/__init__.py
cryptolyzer/httpx/analyzer.py
cryptolyzer/httpx/client.py
cryptolyzer/httpx/content.py
cryptolyzer/httpx/headers.py
cryptolyzer/httpx/transfer.py
cryptolyzer/ja3/__init__.py
cryptolyzer/ja3/analyzer.py
cryptolyzer/ja3/decode.py
cryptolyzer/ja3/generate.py
cryptolyzer/ssh/__init__.py
cryptolyzer/ssh/all.py
cryptolyzer/ssh/analyzer.py
cryptolyzer/ssh/ciphers.py
cryptolyzer/ssh/client.py
cryptolyzer/ssh/dhparams.py
cryptolyzer/ssh/exception.py
cryptolyzer/ssh/pubkeys.py
cryptolyzer/ssh/server.py
cryptolyzer/ssh/transfer.py
cryptolyzer/ssh/versions.py
cryptolyzer/ssh/vulnerabilities.py
cryptolyzer/tls/__init__.py
cryptolyzer/tls/all.py
cryptolyzer/tls/analyzer.py
cryptolyzer/tls/application.py
cryptolyzer/tls/ciphers.py
cryptolyzer/tls/client.py
cryptolyzer/tls/curves.py
cryptolyzer/tls/dhparams.py
cryptolyzer/tls/exception.py
cryptolyzer/tls/extensions.py
cryptolyzer/tls/pubkeyreq.py
cryptolyzer/tls/pubkeys.py
cryptolyzer/tls/server.py
cryptolyzer/tls/sigalgos.py
cryptolyzer/tls/simulations.py
cryptolyzer/tls/versions.py
cryptolyzer/tls/vulnerabilities.py
cryptolyzer-1.0.2.dist-info/licenses/LICENSE.txt
docs/.gitignore
docs/api.rst
docs/changelog.rst
docs/cli.rst
docs/conf.py
docs/development.rst
docs/features.rst
docs/index.rst
docs/installation.rst
test/__init__.py
test/test_main.py
test/common/__init__.py
cryptolyzer-1.0.2.dist-info/METADATA
cryptolyzer-1.0.2.dist-info/WHEEL
cryptolyzer-1.0.2.dist-info/entry_points.txt
cryptolyzer-1.0.2.dist-info/top_level.txt
cryptolyzer-1.0.2.dist-info/RECORD
