Metadata-Version: 2.4
Name: CryptoLyzer
Version: 1.0.2
Summary: A comprehensive cryptographic settings analyzer
Author-email: Szilárd Pfeiffer <coroner@pfeifferszilard.hu>
Maintainer-email: Szilárd Pfeiffer <coroner@pfeifferszilard.hu>
License: MPL-2.0
Project-URL: Homepage, https://gitlab.com/coroner/cryptolyzer
Project-URL: Changelog, https://cryptolyzer.readthedocs.io/en/latest/changelog
Project-URL: Documentation, https://cryptolyzer.readthedocs.io/en/latest/
Project-URL: Issues, https://gitlab.com/coroner/cryptolyzer/-/issues
Project-URL: Source, https://gitlab.com/coroner/cryptolyzer
Keywords: ssl,tls,gost,ja3,hassh,https,pop3,smtp,imap,ftp,rdp,xmpp,jabber,ldap,sieve,ssh,hsts,dnssec
Classifier: Development Status :: 5 - Production/Stable
Classifier: Environment :: Console
Classifier: Framework :: tox
Classifier: Intended Audience :: Developers
Classifier: Intended Audience :: Information Technology
Classifier: Intended Audience :: Science/Research
Classifier: Intended Audience :: System Administrators
Classifier: Natural Language :: English
Classifier: Operating System :: MacOS
Classifier: Operating System :: Microsoft :: Windows
Classifier: Operating System :: POSIX
Classifier: Programming Language :: Python :: 3.9
Classifier: Programming Language :: Python :: 3.10
Classifier: Programming Language :: Python :: 3.11
Classifier: Programming Language :: Python :: 3.12
Classifier: Programming Language :: Python :: 3.13
Classifier: Programming Language :: Python :: 3.14
Classifier: Programming Language :: Python :: Implementation :: CPython
Classifier: Programming Language :: Python :: Implementation :: PyPy
Classifier: Programming Language :: Python
Classifier: Topic :: Internet
Classifier: Topic :: Internet :: File Transfer Protocol (FTP)
Classifier: Topic :: Internet :: XMPP
Classifier: Topic :: Security
Classifier: Topic :: Security :: Cryptography
Classifier: Topic :: Software Development :: Libraries :: Python Modules
Classifier: Topic :: Software Development :: Testing :: Traffic Generation
Classifier: Topic :: Software Development :: Testing
License-File: LICENSE.txt
Requires-Dist: attrs
Requires-Dist: bs4
Requires-Dist: certvalidator
Requires-Dist: colorama
Requires-Dist: cryptoparser==1.0.2
Requires-Dist: pyfakefs
Requires-Dist: python-dateutil
Requires-Dist: requests
Requires-Dist: dnspython
Requires-Dist: urllib3
Provides-Extra: docs
Requires-Dist: sphinx>=8.0; extra == "docs"
Requires-Dist: sphinx-sitemap; extra == "docs"
Dynamic: license-file
